greet_kyh/__init__.py
greet_kyh/greeter.py
greet_kyh-1.0.dist-info/LICENSE
greet_kyh-1.0.dist-info/METADATA
greet_kyh-1.0.dist-info/WHEEL
greet_kyh-1.0.dist-info/top_level.txt
greet_kyh-1.0.dist-info/RECORD
